medroom/dna/processors/__init__.py
medroom/dna/processors/config.py
medroom/dna/processors/main.py
medroom/dna/processors/utils/__init__.py
medroom/dna/processors/utils/evalmetrics.py
medroom/dna/processors/utils/mlflow_helper.py
medroom/dna/processors/utils/textclean.py
MedRoom.AI.DataEngineer-0.0.17.dist-info/LICENSE
MedRoom.AI.DataEngineer-0.0.17.dist-info/METADATA
MedRoom.AI.DataEngineer-0.0.17.dist-info/WHEEL
MedRoom.AI.DataEngineer-0.0.17.dist-info/dependency_links.txt
MedRoom.AI.DataEngineer-0.0.17.dist-info/top_level.txt
MedRoom.AI.DataEngineer-0.0.17.dist-info/RECORD
