Metadata-Version: 2.1
Name: MedRoom.AI.DataEngineer
Version: 0.0.17
Summary: A Natural Language Processing Data Engineer
Home-page: https://github.com/MedRoomGitHub/MedRoom.AI.DataEngineer
Author: Team IA
Author-email: medroom@medroom.com.br
License: Apache License
Requires-Python: >=3.8
License-File: LICENSE
Requires-Dist: nltk ==3.8.1
Requires-Dist: spacy ==3.7.1
Requires-Dist: unidecode ==1.3.7
Requires-Dist: pandas ==2.1.1
Requires-Dist: numpy ==1.26.0
Requires-Dist: scikit-learn ==1.3.1
Requires-Dist: mlflow ==2.12.2
Requires-Dist: transformers ==4.49.0
Requires-Dist: boto3 ==1.34.113
Provides-Extra: plotting
Requires-Dist: matplotlib ==3.7.0 ; extra == 'plotting'
Requires-Dist: seaborn ==0.13.0 ; extra == 'plotting'
